cdeid/__init__.py
cdeid/__main__.py
cdeid/data/__init__.py
cdeid/data/data_loader.py
cdeid/data/data_operator.py
cdeid/data/document.py
cdeid/deidentifier/__init__.py
cdeid/deidentifier/annotator.py
cdeid/deidentifier/phi_deid.py
cdeid/display/__init__.py
cdeid/display/html_generator.py
cdeid/models/__init__.py
cdeid/models/ensemble_model.py
cdeid/models/flair_trainer.py
cdeid/models/spacy_trainer.py
cdeid/models/stanza_trainer.py
cdeid/models/stanza_trainer_agent.py
cdeid/models/trainer.py
cdeid/utils/__init__.py
cdeid/utils/converter.py
cdeid/utils/resources.py
cdeid/utils/scorer.py
cdeid-0.1.3.dist-info/LICENSE
cdeid-0.1.3.dist-info/METADATA
cdeid-0.1.3.dist-info/WHEEL
cdeid-0.1.3.dist-info/top_level.txt
cdeid-0.1.3.dist-info/RECORD
