Metadata-Version: 2.1
Name: cdeid
Version: 0.1.3
Summary: A Customized De-identification framework
Home-page: https://github.com/CBDRH/cdeid
Author: Leibo Liu
Author-email: liuleibo@gmail.com
License: UNKNOWN
Keywords: DE-IDENTIFICATION,NLP
Platform: UNKNOWN
Classifier: Development Status :: 3 - Alpha
Classifier: Programming Language :: Python :: 3
Classifier: License :: OSI Approved :: Apache Software License
Classifier: Operating System :: OS Independent
Requires-Python: >=3.7
Requires-Dist: spaCy (>=2.3.2)
Requires-Dist: stanza (>=1.1.1)
Requires-Dist: flair (==0.8)
Requires-Dist: mako (>=1.1.3)
